compare_my_stocks/__init__.py
compare_my_stocks/__main__.py
compare_my_stocks/app.py
compare_my_stocks/common/__init__.py
compare_my_stocks/common/autoreloader.py
compare_my_stocks/common/common.py
compare_my_stocks/common/dolongprocess.py
compare_my_stocks/common/impacketLICENSE
compare_my_stocks/common/logger.py
compare_my_stocks/common/loghandler.py
compare_my_stocks/common/orederedset.py
compare_my_stocks/common/paramaware.py
compare_my_stocks/common/refvar.py
compare_my_stocks/common/simpleexceptioncontext.py
compare_my_stocks/config/__init__.py
compare_my_stocks/config/newconfig.py
compare_my_stocks/conftest.py
compare_my_stocks/data/example_mystock.csv
compare_my_stocks/data/graphs.json
compare_my_stocks/data/groups.json
compare_my_stocks/data/hist_file.cache
compare_my_stocks/data/jupyter/defaultnotebook.ipynb
compare_my_stocks/data/myconfig.yaml
compare_my_stocks/engine/__init__.py
compare_my_stocks/engine/compareengine.py
compare_my_stocks/engine/compareengineinterface.py
compare_my_stocks/engine/parameters.py
compare_my_stocks/engine/symbols.py
compare_my_stocks/engine/symbolshandler.py
compare_my_stocks/engine/symbolsinterface.py
compare_my_stocks/graph/__init__.py
compare_my_stocks/graph/graphgenerator.py
compare_my_stocks/gui/__init__.py
compare_my_stocks/gui/daterangeslider.py
compare_my_stocks/gui/forminitializer.py
compare_my_stocks/gui/forminitializerinterface.py
compare_my_stocks/gui/forminterface.py
compare_my_stocks/gui/formobserver.py
compare_my_stocks/gui/formobserverinterface.py
compare_my_stocks/gui/graphhandler.py
compare_my_stocks/gui/jupyterhandler.py
compare_my_stocks/gui/listobserver.py
compare_my_stocks/gui/mainwindow.py
compare_my_stocks/gui/mainwindow.ui
compare_my_stocks/gui/stockchoice.py
compare_my_stocks/ib/__init__.py
compare_my_stocks/ib/remoteprocess.py
compare_my_stocks/ib/timeoutreg.py
compare_my_stocks/ibsrv.py
compare_my_stocks/input/__init__.py
compare_my_stocks/input/earningscommon.py
compare_my_stocks-1.0.5.dist-info/LICENSE
compare_my_stocks-1.0.5.dist-info/METADATA
compare_my_stocks-1.0.5.dist-info/WHEEL
compare_my_stocks-1.0.5.dist-info/RECORD
