Metadata-Version: 2.1
Name: compare-my-stocks
Version: 1.0.5
Summary: A system for visualizing interesting stocks. Has powerful comparison capabilities and works seamlessly with your jupyter notebook.   Written in QT with matplotlib.
Author: eyalk5
Requires-Python: >=3.9,<3.11
Classifier: Programming Language :: Python :: 3
Classifier: Programming Language :: Python :: 3.9
Classifier: Programming Language :: Python :: 3.10
Provides-Extra: full
Provides-Extra: jupyter
Provides-Extra: mini
Requires-Dist: colorlog (>=6.7.0,<6.8.0) ; extra == "full" or extra == "mini" or extra == "jupyter"
Requires-Dist: dacite (>=1.8.1,<2.0.0)
Requires-Dist: dataconf (>=2.1.3,<2.1.4) ; extra == "full"
Requires-Dist: django (>=3.2.9,<3.2.10) ; extra == "full" or extra == "mini" or extra == "jupyter"
Requires-Dist: ib-insync (>=0.9.85,<0.10.0) ; extra == "full"
Requires-Dist: ibflex (>=0.15,<1.0) ; extra == "full"
Requires-Dist: ipykernel ; extra == "full" or extra == "jupyter"
Requires-Dist: json-editor-pyside6 (>=1.0.3,<2.0.0) ; extra == "full"
Requires-Dist: jupyter-server (>=2.7.3,<3.0.0)
Requires-Dist: matplotlib (==3.5.0rc1) ; extra == "full"
Requires-Dist: memoization (==0.4.0)
Requires-Dist: mplcursors (>=0.4,<1.0) ; extra == "full"
Requires-Dist: nbformat (>=5.7.3,<5.8.0) ; extra == "full"
Requires-Dist: notebook (==7.0.3)
Requires-Dist: numpy (>=1.22.0,<1.23.0) ; extra == "full" or extra == "mini" or extra == "jupyter"
Requires-Dist: pandas (==1.3.2) ; extra == "full"
Requires-Dist: psutil (>=5.8.0,<5.9.0) ; extra == "full"
Requires-Dist: pyro5 (>=5.14,<6.0) ; extra == "full"
Requires-Dist: pyside6 (>=6.2.0,<6.3.0) ; extra == "full"
Requires-Dist: pytest (>=7.3.0,<8.0.0) ; extra == "full"
Requires-Dist: python-dateutil (>=2.8.2,<2.8.3)
Requires-Dist: pytz (>=2021.3,<2022.0) ; extra == "full"
Requires-Dist: qt-collapsible-section-pyside6 (>=0.1.0,<0.2.0) ; extra == "full"
Requires-Dist: qtvoila (==2.1.0) ; extra == "full"
Requires-Dist: requests (>=2.28.0) ; extra == "full"
Requires-Dist: ruamel.yaml (>=0.17.31,<0.18.0) ; extra == "full" or extra == "mini" or extra == "jupyter"
Requires-Dist: setuptools (>=60.2.0,<60.3.0) ; extra == "full"
Requires-Dist: six (>=1.16.0,<1.17.0) ; extra == "full"
Requires-Dist: superqt (>=0.2.5.post1,<0.3.0) ; extra == "full"
Requires-Dist: toml (>=0.10.2,<0.11.0) ; extra == "full"
Requires-Dist: voila ; extra == "jupyter"
